{"inkVersion":21,"root":[["^This is test 2","\n",{"->":"main"},["done",{"#f":5,"#n":"g-0"}],null],"done",{"main":[["ev","str","^<i>\"lets rest for now\"","/str","/ev",{"*":".^.c-0","flg":20},"ev","str","^<i>\"Let's continue for a while more\"","/str","/ev",{"*":".^.c-1","flg":20},"ev","str","^Ignore","/str","/ev",{"*":".^.c-2","flg":20},{"c-0":["^ ","\n","^Alright, let's stop up for now ","#","^testTag4","/#","\n","end",{"#f":5}],"c-1":["\n","^we shall continue then ","#","^testTag3","/#","\n",{"->":"continue"},{"#f":5}],"c-2":["\n","^<i>\"Hello, can you hear me?? why aren't you answering me?\"","\n",{"->":"next"},{"#f":5}]}],{"#f":1}],"next":[["ev","str","^turn around and start to eat your crewmate","/str","/ev",{"*":".^.c-0","flg":20},{"c-0":["\n","^<i>\"Oh, you finally noticed i was talking to you... why are you ominously moving towards me?\" ","#","^testTag1","/#","\n",{"->":"next.third"},{"#f":5}]}],{"third":[["ev","str","^take a bite","/str","/ev",{"*":".^.c-0","flg":20},{"c-0":["\n","^You take a huge bite","\n","^<i>\"The captain has gone crazy, SHOOT HIM!\"","\n","^<color=red> die from gunshot</color> ","#","^testTag2","/#","\n","end",{"#f":5}]}],{"#f":1}],"#f":1}],"continue":[["ev","str","^let's stop now","/str","/ev",{"*":".^.c-0","flg":20},{"c-0":["\n","^We have walked for a while now, I think we should rest now before it becomes too dangerous","\n",{"->":"main"},{"#f":5}]}],{"#f":1}],"#f":1}],"listDefs":{}}